<annotation>
	<folder>dataset</folder>
	<filename>frame405.jpg</filename>
	<path>/home/serkan/git/Teknofest2018Robotaksi/dataset/frame405.jpg</path>
	<source>
		<database>Unknown</database>
	</source>
	<size>
		<width>640</width>
		<height>352</height>
		<depth>3</depth>
	</size>
	<segmented>0</segmented>
	<object>
		<name>saga_donulmez</name>
		<pose>Unspecified</pose>
		<truncated>0</truncated>
		<difficult>0</difficult>
		<bndbox>
			<xmin>338</xmin>
			<ymin>78</ymin>
			<xmax>453</xmax>
			<ymax>214</ymax>
		</bndbox>
	</object>
	<object>
		<name>park_yapilmaz</name>
		<pose>Unspecified</pose>
		<truncated>0</truncated>
		<difficult>0</difficult>
		<bndbox>
			<xmin>282</xmin>
			<ymin>90</ymin>
			<xmax>322</xmax>
			<ymax>128</ymax>
		</bndbox>
	</object>
</annotation>
